kappaml/__init__.py
kappaml/kappaml.py
kappaml-1.1.0.dist-info/licenses/LICENSE
kappaml-1.1.0.dist-info/METADATA
kappaml-1.1.0.dist-info/WHEEL
kappaml-1.1.0.dist-info/top_level.txt
kappaml-1.1.0.dist-info/RECORD
