Metadata-Version: 2.4
Name: kappaml
Version: 1.1.0
Summary: A Python client to interact with the KappaML platform
Author-email: Alex Imbrea <alex@kappaml.com>
Project-URL: Homepage, https://github.com/kappaml/kappaml-python
Project-URL: Bug Tracker, https://github.com/kappaml/kappaml-python/issues
Classifier: Programming Language :: Python :: 3
Classifier: License :: OSI Approved :: MIT License
Classifier: Operating System :: OS Independent
Classifier: Intended Audience :: Developers
Classifier: Intended Audience :: Science/Research
Classifier: Development Status :: 5 - Production/Stable
Requires-Python: >=3.8
License-File: LICENSE
Requires-Dist: httpx>=0.28.0
Dynamic: license-file
